collective.eeafaceted.dashboard-0.23.0-py3.13-nspkg.pth
collective/eeafaceted/dashboard/__init__.py
collective/eeafaceted/dashboard/adapters.py
collective/eeafaceted/dashboard/columns.py
collective/eeafaceted/dashboard/columns.zcml
collective/eeafaceted/dashboard/config.py
collective/eeafaceted/dashboard/configure.zcml
collective/eeafaceted/dashboard/default_widgets.xml
collective/eeafaceted/dashboard/interfaces.py
collective/eeafaceted/dashboard/mk_sync_locales.sh
collective/eeafaceted/dashboard/overrides.zcml
collective/eeafaceted/dashboard/profiles.zcml
collective/eeafaceted/dashboard/setuphandlers.py
collective/eeafaceted/dashboard/testing.py
collective/eeafaceted/dashboard/testing.zcml
collective/eeafaceted/dashboard/upgrades.zcml
collective/eeafaceted/dashboard/utils.py
collective/eeafaceted/dashboard/vocabulary.py
collective/eeafaceted/dashboard/browser/__init__.py
collective/eeafaceted/dashboard/browser/configure.zcml
collective/eeafaceted/dashboard/browser/facetedcollectionportlet.py
collective/eeafaceted/dashboard/browser/overrides.py
collective/eeafaceted/dashboard/browser/views.py
collective/eeafaceted/dashboard/browser/static/.gitkeep
collective/eeafaceted/dashboard/browser/static/ajax-loader.gif
collective/eeafaceted/dashboard/browser/static/collective.eeafaceted.dashboard.css
collective/eeafaceted/dashboard/browser/static/collective.eeafaceted.dashboard.js
collective/eeafaceted/dashboard/browser/static/dashboardpodtemplate.png
collective/eeafaceted/dashboard/browser/templates/generationlinks.pt
collective/eeafaceted/dashboard/browser/templates/portlet_facetedcollection.pt
collective/eeafaceted/dashboard/browser/templates/term.pt
collective/eeafaceted/dashboard/browser/templates/two_tables.pt
collective/eeafaceted/dashboard/browser/templates/widget.pt
collective/eeafaceted/dashboard/content/__init__.py
collective/eeafaceted/dashboard/content/configure.zcml
collective/eeafaceted/dashboard/content/pod_template.py
collective_eeafaceted_dashboard-0.23.0.dist-info/licenses/LICENSE
collective_eeafaceted_dashboard-0.23.0.dist-info/METADATA
collective_eeafaceted_dashboard-0.23.0.dist-info/WHEEL
collective_eeafaceted_dashboard-0.23.0.dist-info/entry_points.txt
collective_eeafaceted_dashboard-0.23.0.dist-info/namespace_packages.txt
collective_eeafaceted_dashboard-0.23.0.dist-info/top_level.txt
collective_eeafaceted_dashboard-0.23.0.dist-info/RECORD
