Metadata-Version: 2.4
Name: collective.eeafaceted.dashboard
Version: 0.23.0
Summary: This package is the glue between different packages offering a usable and integrated dashboard application
Home-page: http://pypi.python.org/pypi/collective.eeafaceted.dashboard
Author: IMIO
Author-email: dev@imio.be
License: GPL V2
Keywords: Python Zope Plone
Classifier: Development Status :: 6 - Mature
Classifier: Environment :: Web Environment
Classifier: Framework :: Plone
Classifier: Framework :: Plone :: 4.3
Classifier: Framework :: Plone :: 5.0
Classifier: Framework :: Plone :: 5.1
Classifier: Programming Language :: Python
Classifier: Programming Language :: Python :: 2.7
License-File: LICENSE
Requires-Dist: Products.ZCatalog
Requires-Dist: plone.api
Requires-Dist: plone.batching>1.0.4
Requires-Dist: setuptools
Requires-Dist: collective.compoundcriterion
Requires-Dist: collective.documentgenerator>3.19
Requires-Dist: collective.eeafaceted.collectionwidget>0.9
Requires-Dist: collective.eeafaceted.z3ctable>1.0
Requires-Dist: eea.facetednavigation>=10.0
Requires-Dist: imio.prettylink
Requires-Dist: z3c.unconfigure
Provides-Extra: test
Requires-Dist: plone.app.dexterity; extra == "test"
Requires-Dist: plone.app.testing; extra == "test"
Requires-Dist: plone.app.relationfield; extra == "test"
Requires-Dist: plone.app.robotframework[reload,ride]; extra == "test"
Requires-Dist: robotframework-selenium2screenshots; extra == "test"
Dynamic: author
Dynamic: author-email
Dynamic: classifier
Dynamic: description
Dynamic: home-page
Dynamic: keywords
Dynamic: license
Dynamic: license-file
Dynamic: provides-extra
Dynamic: requires-dist
Dynamic: summary
